cbr_user_session/User_Session__Config.py
cbr_user_session/User_Session__Shared_Objects.py
cbr_user_session/__init__.py
cbr_user_session/backend/__init__.py
cbr_user_session/fast_api/User_Session__Fast_API.py
cbr_user_session/fast_api/__init__.py
cbr_user_session/fast_api/routes/Routes__Guest.py
cbr_user_session/fast_api/routes/Routes__Guests.py
cbr_user_session/fast_api/routes/Routes__Info.py
cbr_user_session/fast_api/routes/Routes__Session.py
cbr_user_session/fast_api/routes/__init__.py
cbr_user_session/lambdas/__init__.py
cbr_user_session/lambdas/handler.py
cbr_user_session/schemas/__init__.py
cbr_user_session/user_session/User_Session__Utils.py
cbr_user_session/user_session/__init__.py
cbr_user_session/utils/Version.py
cbr_user_session/utils/__init__.py
cbr_user_session/version
cbr_user_session-0.7.13.dist-info/LICENSE
cbr_user_session-0.7.13.dist-info/METADATA
cbr_user_session-0.7.13.dist-info/WHEEL
cbr_user_session-0.7.13.dist-info/RECORD
